{
  "version": 1,
  "updated_at": 1782659053,
  "user_id": "2e9c59f922a30781fe2e62d7524fd691fac997cd",
  "name": "jinjiali",
  "avatar": "https://pic1.afdiancdn.com/user/user_upload_osl/0f46cf7e734fd93047fa2983a7609803_w100_h100_s2.jpeg",
  "amount": 15.0,
  "level": 1,
  "plan_name": "自选方案",
  "sponsor": true,
  "orders": [
    {
      "out_trade_no": "202606071129309748102929193",
      "amount": 10.0
    },
    {
      "out_trade_no": "202605262116291005348512808",
      "amount": 5.0
    }
  ]
}
